LICENSE
MANIFEST.in
README.md
pyproject.toml
setup.cfg
protfasta/__init__.py
protfasta/_configs.py
protfasta/_version.py
protfasta/io.py
protfasta/protfasta.py
protfasta/protfasta_exceptions.py
protfasta/utilities.py
protfasta.egg-info/PKG-INFO
protfasta.egg-info/SOURCES.txt
protfasta.egg-info/dependency_links.txt
protfasta.egg-info/entry_points.txt
protfasta.egg-info/not-zip-safe
protfasta.egg-info/requires.txt
protfasta.egg-info/top_level.txt
protfasta/data/README.md
protfasta/data/look_and_say.dat
protfasta/data/test_data/aligned_seq_all_valid.fasta
protfasta/data/test_data/aligned_seq_all_valid_convertable.fasta
protfasta/data/test_data/aligned_seq_all_valid_unconvertable.fasta
protfasta/data/test_data/fixable_invalid.fasta
protfasta/data/test_data/test_data_with_bad_chars.fa
protfasta/data/test_data/test_data_with_nonstandard_chars.fa
protfasta/data/test_data/testset_1.fasta
protfasta/data/test_data/testset_duplicate.fasta
protfasta/data/test_data/testset_duplicate_seqs.fasta
protfasta/data/test_data/unfixable_invalid.fasta
protfasta/scripts/__init__.py
protfasta/scripts/pfasta.py
protfasta/tests/__init__.py
protfasta/tests/conftest.py
protfasta/tests/test_protfasta.py
protfasta/tests/outdata/readme.md
protfasta/tests/outdata/test_out_1.fasta
protfasta/tests/outdata/test_out_2.fasta
protfasta/tests/pfasta_test/100_seqs_with_allvalid.fasta
protfasta/tests/pfasta_test/100_seqs_with_invalid.fasta
protfasta/tests/pfasta_test/input_test.fasta
protfasta/tests/pfasta_test/run_coverage_tests.sh