Metadata-Version: 2.1
Name: protfasta
Version: 0.1.15.2
Summary: Lightweight package for reading and writing FASTA files.
Author-email: Alex Holehouse <alex.holehouse@wustl.edu>
License: MIT
Requires-Python: >=3.7
License-File: LICENSE
Provides-Extra: test
Requires-Dist: pytest>=6.1.2; extra == "test"
